{
	"name": "clara.server.tools.graph.rules.loan_app_facts.DocumentCheck",
	"count": 1,
	"inserted-from": [
		{
			"name": "clara.server.tools.graph.rules.loan-doc-rules/app-has-all-required-docs",
			"type": "rule",
			"facts": [
				{
					"id": 9,
					"type": "clara.server.tools.graph.rules.loan_app_facts.DocumentCheck",
					"data": {
						"app-id": "app-1",
						"status": "pass",
						"message": "All required documents found"
					},
					"is-root": false,
					"inserted-from": [
						{
							"name": "clara.server.tools.graph.rules.loan-doc-rules/app-has-all-required-docs",
							"ns": "clara.server.tools.graph.rules.loan-doc-rules",
							"type": "rule"
						}
					],
					"used-by": [
						{
							"name": "clara.server.tools.graph.rules.loan-doc-rules/find-document-check",
							"ns": "",
							"type": "query"
						},
						{
							"name": "clara.server.tools.graph.rules.loan-app-rules/app-outcome-approved",
							"ns": "clara.server.tools.graph.rules.loan-app-rules",
							"type": "rule"
						}
					]
				}
			],
			"ns": "clara.server.tools.graph.rules.loan-doc-rules"
		}
	],
	"used-by": [
		{
			"name": "clara.server.tools.graph.rules.loan-doc-rules/find-document-check",
			"type": "query",
			"facts": [
				{
					"id": 9,
					"type": "clara.server.tools.graph.rules.loan_app_facts.DocumentCheck",
					"data": {
						"app-id": "app-1",
						"status": "pass",
						"message": "All required documents found"
					},
					"is-root": false,
					"inserted-from": [
						{
							"name": "clara.server.tools.graph.rules.loan-doc-rules/app-has-all-required-docs",
							"ns": "clara.server.tools.graph.rules.loan-doc-rules",
							"type": "rule"
						}
					],
					"used-by": [
						{
							"name": "clara.server.tools.graph.rules.loan-doc-rules/find-document-check",
							"ns": "",
							"type": "query"
						},
						{
							"name": "clara.server.tools.graph.rules.loan-app-rules/app-outcome-approved",
							"ns": "clara.server.tools.graph.rules.loan-app-rules",
							"type": "rule"
						}
					]
				}
			],
			"ns": ""
		},
		{
			"name": "clara.server.tools.graph.rules.loan-app-rules/app-outcome-approved",
			"type": "rule",
			"facts": [
				{
					"id": 9,
					"type": "clara.server.tools.graph.rules.loan_app_facts.DocumentCheck",
					"data": {
						"app-id": "app-1",
						"status": "pass",
						"message": "All required documents found"
					},
					"is-root": false,
					"inserted-from": [
						{
							"name": "clara.server.tools.graph.rules.loan-doc-rules/app-has-all-required-docs",
							"ns": "clara.server.tools.graph.rules.loan-doc-rules",
							"type": "rule"
						}
					],
					"used-by": [
						{
							"name": "clara.server.tools.graph.rules.loan-doc-rules/find-document-check",
							"ns": "",
							"type": "query"
						},
						{
							"name": "clara.server.tools.graph.rules.loan-app-rules/app-outcome-approved",
							"ns": "clara.server.tools.graph.rules.loan-app-rules",
							"type": "rule"
						}
					]
				}
			],
			"ns": "clara.server.tools.graph.rules.loan-app-rules"
		}
	],
	"ids": [9]
}
